{
    "Ar36": {
        "error": 0.0025319934873020778, 
        "fit": "Parabolic", 
        "value": 0.049673806846566693
    }, 
    "Ar37": {
        "error": 0.050023698274291394, 
        "fit": "linear", 
        "value": 0.0034268728576303271
    }, 
    "Ar38": {
        "error": 0.022829437817713058, 
        "fit": "linear", 
        "value": 1.9037696110423641
    }, 
    "Ar39": {
        "error": 0.10805187560726093, 
        "fit": "Parabolic", 
        "value": 158.89653412322764
    }, 
    "Ar40": {
        "error": 0.36829534951132592, 
        "fit": "Parabolic", 
        "value": 2202.988347405515
    }, 
    "Ar41": {
        "error": 0.10390206208838677, 
        "fit": "linear", 
        "value": 0.12107907202299106
    }
}